liikesim/__init__.py
liikesim/_vehicle.py
liikesim/connection.py
liikesim/exceptions.py
liikesim/main.py
liikesim/utils.py
liikesim-0.0.0.dist-info/METADATA
liikesim-0.0.0.dist-info/WHEEL
liikesim-0.0.0.dist-info/top_level.txt
liikesim-0.0.0.dist-info/RECORD
