Metadata-Version: 2.1
Name: liikesim
Version: 0.0.0
Summary: simple test for liikesim
License: Apache-2.0
Keywords: liikesim
